pybluemo/__init__.py
pybluemo/aws_srp.py
pybluemo/core.py
pybluemo/message.py
pybluemo/sensordb.py
pybluemo/sensors.py
pybluemo/util.py
pybluemo-0.16.dist-info/LICENSE
pybluemo-0.16.dist-info/METADATA
pybluemo-0.16.dist-info/WHEEL
pybluemo-0.16.dist-info/top_level.txt
pybluemo-0.16.dist-info/RECORD
