Metadata-Version: 2.1
Name: pybluemo
Version: 0.16
Summary: Interface library for the Bluemo Bluetooth motion controller.
Home-page: https://github.com/mjbrown/pybluemo
Author: Michael Brown
Author-email: mjbrown.droid@gmail.com
License: UNKNOWN
Platform: UNKNOWN
Classifier: Development Status :: 3 - Alpha
Classifier: Intended Audience :: Developers
Classifier: License :: OSI Approved :: Mozilla Public License 2.0 (MPL 2.0)
Classifier: Programming Language :: Python :: 3
Classifier: Programming Language :: Python :: 3.8
Classifier: Topic :: Software Development :: Libraries
Classifier: Operating System :: OS Independent
License-File: LICENSE
Requires-Dist: bgapi
Requires-Dist: boto3
Requires-Dist: python-graphql-client
